hello.py
hello_ta2642-0.0.1.dist-info/LICENSE.txt
hello_ta2642-0.0.1.dist-info/METADATA
hello_ta2642-0.0.1.dist-info/WHEEL
hello_ta2642-0.0.1.dist-info/top_level.txt
hello_ta2642-0.0.1.dist-info/RECORD
