Metadata-Version: 2.1
Name: hello-ta2642
Version: 0.0.1
Summary: basic hello package
Home-page: https://github.com/tamanna-a/package
Author: Tamanna
Author-email: ta2642@columbia.edu
License: UNKNOWN
Platform: UNKNOWN
Classifier: Development Status :: 1 - Planning
Classifier: Intended Audience :: Developers
Classifier: Programming Language :: Python :: 3
Classifier: Operating System :: OS Independent
Classifier: License :: OSI Approved :: GNU General Public License v2 or later (GPLv2+)
License-File: LICENSE.txt
Requires-Dist: blessings (~=1.7)
Provides-Extra: dev
Requires-Dist: pytest (>=3.7) ; extra == 'dev'
